sortednp-0.5.0.dist-info/RECORD
sortednp-0.5.0.dist-info/METADATA
sortednp-0.5.0.dist-info/WHEEL
sortednp-0.5.0.dist-info/LICENSE
sortednp-0.5.0.dist-info/top_level.txt
sortednp/__init__.py
sortednp/_internal.cpython-310-x86_64-linux-gnu.so
sortednp/kway.py
sortednp/tests/test_resolve.py
sortednp/tests/test_issubset.py
sortednp/tests/test_merge_indices.py
sortednp/tests/__init__.py
sortednp/tests/test_random.py
sortednp/tests/test_isitem.py
sortednp/tests/test_kway_intersect.py
sortednp/tests/test_intersect_indices.py
sortednp/tests/test_merge.py
sortednp/tests/test_kway_merge.py
sortednp/tests/test_intersect.py
