Metadata-Version: 2.1
Name: sortednp
Version: 0.5.0
Summary: Merge and intersect sorted numpy arrays.
Home-page: https://sortednp.dev/
Author: Frank Sauerburger
Author-email: frank@sauerburger.com
License: MIT
Keywords: merge intersect sorted numpy
Platform: Linux
Platform: Unix
Classifier: Intended Audience :: Developers
Classifier: License :: OSI Approved :: MIT License
Classifier: Programming Language :: Python :: 3 :: Only
Classifier: Programming Language :: C
Requires-Python: >=3
License-File: LICENSE
Requires-Dist: numpy<2,>=1.17.3
